diffcsv/__init__.py
diffcsv/database.py
diffcsv/main.py
diffcsv/read_csv.py
diffcsv-0.1.dist-info/DESCRIPTION.rst
diffcsv-0.1.dist-info/METADATA
diffcsv-0.1.dist-info/RECORD
diffcsv-0.1.dist-info/WHEEL
diffcsv-0.1.dist-info/entry_points.txt
diffcsv-0.1.dist-info/metadata.json
diffcsv-0.1.dist-info/top_level.txt
