Metadata-Version: 2.0
Name: diffcsv
Version: 0.1
Summary: Find difference between two large csv files
Home-page: https://github.com/ugursogukpinar/diff-csv
Author: Uğur Soğukpınar
Author-email: sogukpinar.ugur@gmail.com
License: LICENSE.txt
Platform: UNKNOWN
Classifier: License :: OSI Approved :: GNU General Public License v3 (GPLv3)
Classifier: Programming Language :: Python :: 3
Classifier: Programming Language :: Python :: 3.3
Classifier: Programming Language :: Python :: 3.4
Classifier: Programming Language :: Python :: 3.5
